discord_lumberjack/__init__.py
discord_lumberjack/handlers/__init__.py
discord_lumberjack/handlers/discord_channel_handler.py
discord_lumberjack/handlers/discord_dm_handler.py
discord_lumberjack/handlers/discord_handler.py
discord_lumberjack/handlers/discord_webhook_handler.py
discord_lumberjack/message_creators/__init__.py
discord_lumberjack/message_creators/basic_message_creator.py
discord_lumberjack/message_creators/chunks.py
discord_lumberjack/message_creators/embed.py
discord_lumberjack/message_creators/embed_long_message_creator.py
discord_lumberjack/message_creators/embed_message_creator.py
discord_lumberjack/message_creators/log_colours.py
discord_lumberjack/message_creators/message_creator.py
discord_lumberjack/py.typed
discord_lumberjack-1.1.3.dist-info/LICENSE
discord_lumberjack-1.1.3.dist-info/WHEEL
discord_lumberjack-1.1.3.dist-info/METADATA
discord_lumberjack-1.1.3.dist-info/RECORD
