Metadata-Version: 2.1
Name: discord-lumberjack
Version: 1.1.3
Summary: A Python logging handler which sends its logs to a Discord Channel
Home-page: https://github.com/abrahammurciano/discord-lumberjack
License: GPLv3
Keywords: discord,logging
Author: Abraham Murciano
Author-email: abrahammurciano@gmail.com
Requires-Python: >=3.8,<4.0
Classifier: License :: Other/Proprietary License
Classifier: Programming Language :: Python :: 3
Classifier: Programming Language :: Python :: 3.10
Classifier: Programming Language :: Python :: 3.8
Classifier: Programming Language :: Python :: 3.9
Requires-Dist: requests (>=2.26,<3.0)
Project-URL: Documentation, https://abrahammurciano.github.io/discord-lumberjack/discord-lumberjack
Project-URL: Repository, https://github.com/abrahammurciano/discord-lumberjack
